academyAI.py
academyAI-1.0.3.dist-info/METADATA
academyAI-1.0.3.dist-info/WHEEL
academyAI-1.0.3.dist-info/top_level.txt
academyAI-1.0.3.dist-info/RECORD
