Metadata-Version: 2.1
Name: academyAI
Version: 1.0.3
Summary: Academy 4 Summer Course
